[{"indicativo":"0252D","nombre":"ARENYS DE MAR","provincia":"BARCELONA","latitud":"413515N","longitud":"023224E","precTot":723,"precSD":9.9958,"tMinMed":13.4331,"tMaxMed":21.7555,"tMed":17.5946,"tMedSD":5.5705,"climate_type":1},{"indicativo":"0076","nombre":"BARCELONA AEROPUERTO","provincia":"BARCELONA","latitud":"411734N","longitud":"020412E","precTot":700.2,"precSD":6.8887,"tMinMed":13.0701,"tMaxMed":21.4183,"tMed":17.2424,"tMedSD":6.0436,"climate_type":1},{"indicativo":"0200E","nombre":"BARCELONA, FABRA","provincia":"BARCELONA","latitud":"412506N","longitud":"020727E","precTot":865.5,"precSD":9.11,"tMinMed":12.5186,"tMaxMed":19.9682,"tMed":16.2452,"tMedSD":5.7972,"climate_type":1},{"indicativo":"0201D","nombre":"BARCELONA","provincia":"BARCELONA","latitud":"412326N","longitud":"021200E","precTot":615.5,"precSD":7.7186,"tMinMed":15.4642,"tMaxMed":20.8348,"tMed":18.1513,"tMedSD":5.1604,"climate_type":1},{"indicativo":"0149X","nombre":"MANRESA","provincia":"BARCELONA","latitud":"414312N","longitud":"015025E","precTot":470.8,"precSD":6.2956,"tMinMed":8.9459,"tMaxMed":21.8877,"tMed":15.4155,"tMedSD":6.8665,"climate_type":4},{"indicativo":"0229I","nombre":"SABADELL AEROPUERTO","provincia":"BARCELONA","latitud":"413125N","longitud":"020611E","precTot":744.3,"precSD":8.0227,"tMinMed":10.6798,"tMaxMed":21.968,"tMed":16.3258,"tMedSD":5.6068,"climate_type":1},{"indicativo":"0255B","nombre":"SANTA SUSANNA","provincia":"BARCELONA","latitud":"413903N","longitud":"024149E","precTot":406.8,"precSD":16.0124,"tMinMed":10.0189,"tMaxMed":18.8986,"tMed":14.4527,"tMedSD":3.9406,"climate_type":1},{"indicativo":"0367","nombre":"GIRONA AEROPUERTO","provincia":"GIRONA","latitud":"415442N","longitud":"024548E","precTot":820,"precSD":9.1914,"tMinMed":10.0758,"tMaxMed":22.3813,"tMed":16.2292,"tMedSD":5.7795,"climate_type":1},{"indicativo":"0324A","nombre":"RIPOLL","provincia":"GIRONA","latitud":"421129N","longitud":"021146E","precTot":709.1,"precSD":6.889,"tMinMed":4.1097,"tMaxMed":19.9714,"tMed":12.0393,"tMedSD":6.5758,"climate_type":3},{"indicativo":"0016A","nombre":"REUS AEROPUERTO","provincia":"TARRAGONA","latitud":"410842N","longitud":"010949E","precTot":593.2,"precSD":7.8388,"tMinMed":12.074,"tMaxMed":22.2624,"tMed":17.1715,"tMedSD":6.024,"climate_type":1},{"indicativo":"0002I","nombre":"VANDELLÒS  ","provincia":"TARRAGONA","latitud":"405729N","longitud":"005217E","precTot":270.1,"precSD":4.7657,"tMinMed":16.3808,"tMaxMed":24.1888,"tMed":20.2855,"tMedSD":4.9039,"climate_type":2},{"indicativo":"1387E","nombre":"A CORUÑA AEROPUERTO","provincia":"A CORUÑA","latitud":"431825N","longitud":"082219W","precTot":726.5,"precSD":4.7644,"tMinMed":10.7208,"tMaxMed":19.7345,"tMed":15.2301,"tMedSD":4.0582,"climate_type":1},{"indicativo":"1387","nombre":"A CORUÑA","provincia":"A CORUÑA","latitud":"432157N","longitud":"082517W","precTot":772.1,"precSD":5.0888,"tMinMed":12.2603,"tMaxMed":18.8231,"tMed":15.5463,"tMedSD":3.6134,"climate_type":1},{"indicativo":"1393","nombre":"CABO VILÁN","provincia":"A CORUÑA","latitud":"430938N","longitud":"091239W","precTot":954.4,"precSD":7.4382,"tMinMed":11.9213,"tMaxMed":16.6257,"tMed":14.2723,"tMedSD":3.1136,"climate_type":1},{"indicativo":"1351","nombre":"ESTACA DE BARES","provincia":"A CORUÑA","latitud":"434710N","longitud":"074106W","precTot":351.4,"precSD":3.7459,"tMinMed":12.9577,"tMaxMed":17.6097,"tMed":15.2831,"tMedSD":3.2523,"climate_type":4},{"indicativo":"1400","nombre":"FISTERRA","provincia":"A CORUÑA","latitud":"425529N","longitud":"091729W","precTot":531,"precSD":5.3444,"tMinMed":11.8366,"tMaxMed":17.0736,"tMed":14.4563,"tMedSD":3.7468,"climate_type":4},{"indicativo":"1437O","nombre":"MONTE IROITE","provincia":"A CORUÑA","latitud":"424314N","longitud":"085524W","precTot":1547,"precSD":9.5805,"tMinMed":8.5153,"tMaxMed":14.6072,"tMed":11.5631,"tMedSD":5.8698,"climate_type":1},{"indicativo":"1473A","nombre":"PADRÓN","provincia":"A CORUÑA","latitud":"424418N","longitud":"083738W","precTot":1092.8,"precSD":9.3362,"tMinMed":9.4673,"tMaxMed":20.0162,"tMed":14.7416,"tMedSD":4.8347,"climate_type":1},{"indicativo":"1428","nombre":"SANTIAGO DE COMPOSTELA AEROPUERTO","provincia":"A CORUÑA","latitud":"425317N","longitud":"082438W","precTot":1020.5,"precSD":6.9711,"tMinMed":8.9133,"tMaxMed":18.1328,"tMed":13.5222,"tMedSD":4.6642,"climate_type":1},{"indicativo":"1475X","nombre":"SANTIAGO DE COMPOSTELA","provincia":"A CORUÑA","latitud":"425234N","longitud":"083321W","precTot":660,"precSD":5.765,"tMinMed":9.9291,"tMaxMed":19.2441,"tMed":14.5847,"tMedSD":4.487,"climate_type":1},{"indicativo":"1212E","nombre":"ASTURIAS AEROPUERTO","provincia":"ASTURIAS","latitud":"433401N","longitud":"060239W","precTot":950.9,"precSD":6.121,"tMinMed":10.4616,"tMaxMed":17.1652,"tMed":13.8129,"tMedSD":3.8515,"climate_type":1},{"indicativo":"1283U","nombre":"CABO BUSTO","provincia":"ASTURIAS","latitud":"433409N","longitud":"062812W","precTot":22,"precSD":1.2363,"tMinMed":11.8097,"tMaxMed":18.2449,"tMed":15.0301,"tMedSD":2.9541,"climate_type":4},{"indicativo":"1210X","nombre":"CABO PEÑAS","provincia":"ASTURIAS","latitud":"433921N","longitud":"055055W","precTot":614.9,"precSD":4.7886,"tMinMed":12.1623,"tMaxMed":16.7123,"tMed":14.4387,"tMedSD":3.6355,"climate_type":1},{"indicativo":"1208H","nombre":"GIJÓN, PUERTO","provincia":"ASTURIAS","latitud":"433336N","longitud":"054203W","precTot":649.7,"precSD":4.0409,"tMinMed":12.346,"tMaxMed":18.4348,"tMed":15.3899,"tMedSD":3.8451,"climate_type":4},{"indicativo":"1183X","nombre":"LLANES","provincia":"ASTURIAS","latitud":"432513N","longitud":"044453W","precTot":747,"precSD":5.346,"tMinMed":11.412,"tMaxMed":17.3722,"tMed":14.39,"tMedSD":3.5643,"climate_type":1},{"indicativo":"1249I","nombre":"OVIEDO","provincia":"ASTURIAS","latitud":"432112N","longitud":"055227W","precTot":792.8,"precSD":5.4053,"tMinMed":9.803,"tMaxMed":18.2463,"tMed":14.0241,"tMedSD":4.5339,"climate_type":1},{"indicativo":"1221D","nombre":"PAJARES-VALGRANDE","provincia":"ASTURIAS","latitud":"425843N","longitud":"054635W","precTot":1280.4,"precSD":7.5891,"tMinMed":4.456,"tMaxMed":11.463,"tMed":7.9582,"tMedSD":5.7557,"climate_type":3},{"indicativo":"1542","nombre":"PUERTO DE LEITARIEGOS","provincia":"ASTURIAS","latitud":"425939N","longitud":"062451W","precTot":554.4,"precSD":5.3087,"tMinMed":2.7169,"tMaxMed":11.2394,"tMed":6.9818,"tMedSD":5.8925,"climate_type":3},{"indicativo":"1082","nombre":"BILBAO AEROPUERTO","provincia":"BIZKAIA","latitud":"431753N","longitud":"025423W","precTot":904.1,"precSD":7.708,"tMinMed":11.4049,"tMaxMed":21.0118,"tMed":16.2101,"tMedSD":4.9292,"climate_type":1},{"indicativo":"1078I","nombre":"GÜEÑES","provincia":"BIZKAIA","latitud":"431212N","longitud":"030617W","precTot":731.6,"precSD":6.1088,"tMinMed":9.7006,"tMaxMed":19.0396,"tMed":14.3731,"tMedSD":5.0373,"climate_type":1},{"indicativo":"1055B","nombre":"LEKEITIO","provincia":"BIZKAIA","latitud":"432237N","longitud":"023037W","precTot":269.7,"precSD":2.2536,"tMinMed":11.9455,"tMaxMed":18.13,"tMed":15.038,"tMedSD":4.5067,"climate_type":4},{"indicativo":"1057B","nombre":"MACHICHACO","provincia":"BIZKAIA","latitud":"432714N","longitud":"024510W","precTot":949.1,"precSD":6.7621,"climate_type":1},{"indicativo":"1059X","nombre":"PUNTA GALEA","provincia":"BIZKAIA","latitud":"432230N","longitud":"030118W","precTot":791.6,"precSD":6.8014,"tMinMed":11.3618,"tMaxMed":18.4873,"tMed":14.9249,"tMedSD":4.3397,"climate_type":1},{"indicativo":"1159","nombre":"SAN VICENTE DE LA BARQUERA","provincia":"CANTABRIA","latitud":"432336N","longitud":"042332W","precTot":622.9,"precSD":3.9839,"tMinMed":11.3693,"tMaxMed":17.4121,"tMed":14.3896,"tMedSD":3.9759,"climate_type":4},{"indicativo":"1109","nombre":"SANTANDER AEROPUERTO","provincia":"CANTABRIA","latitud":"432526N","longitud":"034932W","precTot":904.8,"precSD":6.5182,"tMinMed":11.6118,"tMaxMed":19.4485,"tMed":15.5282,"tMedSD":4.3748,"climate_type":1},{"indicativo":"1111","nombre":"SANTANDER","provincia":"CANTABRIA","latitud":"432928N","longitud":"034802W","precTot":751.5,"precSD":5.5234,"tMinMed":12.6547,"tMaxMed":18.4874,"tMed":15.5723,"tMedSD":3.979,"climate_type":1},{"indicativo":"1024E","nombre":"DONOSTIA/SAN SEBASTIÁN, IGUELDO","provincia":"GIPUZKOA","latitud":"431823N","longitud":"020228W","precTot":1400.9,"precSD":9.0524,"tMinMed":11.5707,"tMaxMed":17.3751,"tMed":14.474,"tMedSD":4.6499,"climate_type":1},{"indicativo":"1050J","nombre":"ELGOIBAR","provincia":"GIPUZKOA","latitud":"431234N","longitud":"022448W","precTot":1104.2,"precSD":11.8517,"tMinMed":10.2495,"tMaxMed":18.7593,"tMed":14.5064,"tMedSD":4.915,"climate_type":1},{"indicativo":"1014","nombre":"HONDARRIBIA, MALKARROA","provincia":"GIPUZKOA","latitud":"432125N","longitud":"014732W","precTot":1438.1,"precSD":9.3561,"tMinMed":11.6926,"tMaxMed":19.5132,"tMed":15.6036,"tMedSD":4.9011,"climate_type":1},{"indicativo":"1014A","nombre":"SAN SEBASTIÁN AEROPUERTO","provincia":"GIPUZKOA","latitud":"432125N","longitud":"014732W","precTot":344.6,"precSD":10.1898,"tMinMed":8.5213,"tMaxMed":16.0082,"tMed":12.2656,"tMedSD":3.6494,"climate_type":3},{"indicativo":"1041A","nombre":"ZUMAIA","provincia":"GIPUZKOA","latitud":"431808N","longitud":"021504W","precTot":864,"precSD":5.5812,"tMinMed":11.5772,"tMaxMed":18.4457,"tMed":15.0142,"tMedSD":4.3024,"climate_type":1},{"indicativo":"1037Y","nombre":"ZUMARRAGA","provincia":"GIPUZKOA","latitud":"430448N","longitud":"021903W","precTot":1120.4,"precSD":10.26,"tMinMed":7.9092,"tMaxMed":16.7684,"tMed":12.3391,"tMedSD":5.4334,"climate_type":1},{"indicativo":"1549","nombre":"PONFERRADA","provincia":"LEON","latitud":"423350N","longitud":"063600W","precTot":459.4,"precSD":3.5548,"tMinMed":7.4216,"tMaxMed":20.4723,"tMed":13.9463,"tMedSD":6.4297,"climate_type":4},{"indicativo":"1505","nombre":"LUGO AEROPUERTO","provincia":"LUGO","latitud":"430641N","longitud":"072727W","precTot":903.3,"precSD":7.1855,"tMinMed":7.0822,"tMaxMed":18.9153,"tMed":12.9967,"tMedSD":5.0605,"climate_type":1},{"indicativo":"1002Y","nombre":"BAZTAN, IRURITA ","provincia":"NAVARRA","latitud":"430809N","longitud":"013235W","precTot":821.3,"precSD":11.8505,"tMinMed":8.9879,"tMaxMed":18.5727,"tMed":13.7788,"tMedSD":5.0568,"climate_type":1},{"indicativo":"1631E","nombre":"A POBRA DE TRIVES","provincia":"OURENSE","latitud":"422022N","longitud":"071657W","precTot":511.5,"precSD":4.7717,"tMinMed":6.1277,"tMaxMed":17.5513,"tMed":11.8389,"tMedSD":5.7407,"climate_type":3},{"indicativo":"1700X","nombre":"O CARBALLIÑO","provincia":"OURENSE","latitud":"422517N","longitud":"080533W","precTot":1051.8,"precSD":8.7653,"tMinMed":6.8178,"tMaxMed":20.9468,"tMed":13.8805,"tMedSD":5.6534,"climate_type":1},{"indicativo":"1690A","nombre":"OURENSE","provincia":"OURENSE","latitud":"421931N","longitud":"075135W","precTot":770,"precSD":6.7729,"tMinMed":8.8252,"tMaxMed":22.9408,"tMed":15.8827,"tMedSD":5.8403,"climate_type":1},{"indicativo":"1735X","nombre":"XINZO DE LIMIA","provincia":"OURENSE","latitud":"420445N","longitud":"074401W","precTot":592.9,"precSD":5.0726,"tMinMed":7.3632,"tMaxMed":20.2866,"tMed":13.8271,"tMedSD":5.3477,"climate_type":4},{"indicativo":"1484C","nombre":"PONTEVEDRA","provincia":"PONTEVEDRA","latitud":"422618N","longitud":"083657W","precTot":1367,"precSD":10.0753,"tMinMed":10.9499,"tMaxMed":19.7959,"tMed":15.3773,"tMedSD":4.6401,"climate_type":1},{"indicativo":"1495","nombre":"VIGO AEROPUERTO","provincia":"PONTEVEDRA","latitud":"421419N","longitud":"083726W","precTot":1418.3,"precSD":11.5379,"tMinMed":10.9722,"tMaxMed":19.5425,"tMed":15.2572,"tMedSD":4.4225,"climate_type":1},{"indicativo":"2444","nombre":"ÁVILA","provincia":"AVILA","latitud":"403933N","longitud":"044048W","precTot":356.7,"precSD":2.8905,"tMinMed":6.6211,"tMaxMed":18.294,"tMed":12.4573,"tMedSD":6.882,"climate_type":4},{"indicativo":"2811A","nombre":"NAVARREDONDA DE GREDOS","provincia":"AVILA","latitud":"402102N","longitud":"050835W","precTot":343.5,"precSD":4.0162,"tMinMed":1.9329,"tMaxMed":15.4422,"tMed":8.6864,"tMedSD":6.3537,"climate_type":3},{"indicativo":"2117D","nombre":"ARANDA DE DUERO","provincia":"BURGOS","latitud":"413957N","longitud":"034434W","precTot":233.6,"precSD":2.282,"tMinMed":5.1771,"tMaxMed":19.8972,"tMed":12.5347,"tMedSD":6.8537,"climate_type":4},{"indicativo":"2331","nombre":"BURGOS AEROPUERTO","provincia":"BURGOS","latitud":"422125N","longitud":"033713W","precTot":504.7,"precSD":4.1915,"tMinMed":5.4677,"tMaxMed":17.4712,"tMed":11.4701,"tMedSD":6.2913,"climate_type":3},{"indicativo":"2298","nombre":"PALACIOS DE LA SIERRA","provincia":"BURGOS","latitud":"415735N","longitud":"030754W","precTot":422.2,"precSD":4.2188,"tMinMed":2.9732,"tMaxMed":16.6431,"tMed":9.8094,"tMedSD":6.2204,"climate_type":3},{"indicativo":"2737E","nombre":"LAGUNAS DE SOMOZA","provincia":"LEON","latitud":"422239N","longitud":"061148W","precTot":335.7,"precSD":4.0599,"tMinMed":3.9263,"tMaxMed":16.3385,"tMed":10.1341,"tMedSD":5.8703,"climate_type":3},{"indicativo":"2661","nombre":"LEÓN, VIRGEN DEL CAMINO","provincia":"LEON","latitud":"423518N","longitud":"053904W","precTot":502.4,"precSD":4.0527,"tMinMed":5.9249,"tMaxMed":17.6679,"tMed":11.7964,"tMedSD":6.3279,"climate_type":3},{"indicativo":"2630X","nombre":"PUERTO DE SAN ISIDRO","provincia":"LEON","latitud":"430344N","longitud":"052237W","precTot":822.8,"precSD":6.1018,"tMinMed":2.4883,"tMaxMed":12.2619,"tMed":7.3768,"tMedSD":5.6327,"climate_type":3},{"indicativo":"2462","nombre":"PUERTO DE NAVACERRADA","provincia":"MADRID","latitud":"404735N","longitud":"040038W","precTot":1291.7,"precSD":8.7095,"tMinMed":3.9468,"tMaxMed":12.3734,"tMed":8.159,"tMedSD":7.2898,"climate_type":3},{"indicativo":"2400E","nombre":"AUTILLA DEL PINO","provincia":"PALENCIA","latitud":"415944N","longitud":"043610W","precTot":326.3,"precSD":2.7502,"tMinMed":6.3072,"tMaxMed":17.4419,"tMed":11.8753,"tMedSD":6.5739,"climate_type":3},{"indicativo":"2374X","nombre":"CARRIÓN DE LOS CONDES","provincia":"PALENCIA","latitud":"422103N","longitud":"043702W","precTot":293,"precSD":2.8119,"tMinMed":5.229,"tMaxMed":18.3759,"tMed":11.8028,"tMedSD":6.1856,"climate_type":3},{"indicativo":"2235U","nombre":"CERVERA DE PISUERGA","provincia":"PALENCIA","latitud":"425214N","longitud":"043112W","precTot":663.2,"precSD":6.4246,"tMinMed":4.3508,"tMaxMed":16.1218,"tMed":10.2383,"tMedSD":6.1767,"climate_type":3},{"indicativo":"2491C","nombre":"LA COVATILLA, ESTACIÓN DE ESQUÍ","provincia":"SALAMANCA","latitud":"402118N","longitud":"054124W","precTot":991.6,"precSD":14.8731,"tMinMed":2.4064,"tMaxMed":9.2814,"tMed":5.8482,"tMedSD":5.9869,"climate_type":3},{"indicativo":"2946X","nombre":"SAELICES EL CHICO","provincia":"SALAMANCA","latitud":"403806N","longitud":"063600W","precTot":161.4,"precSD":4.392,"tMinMed":6.7847,"tMaxMed":20.26,"tMed":13.5218,"tMedSD":6.6849,"climate_type":4},{"indicativo":"2867","nombre":"SALAMANCA AEROPUERTO","provincia":"SALAMANCA","latitud":"405734N","longitud":"052954W","precTot":246.8,"precSD":1.946,"tMinMed":5.6124,"tMaxMed":20.5022,"tMed":13.058,"tMedSD":6.4896,"climate_type":4},{"indicativo":"2870","nombre":"SALAMANCA","provincia":"SALAMANCA","latitud":"405727N","longitud":"053944W","precTot":304.4,"precSD":2.7819,"tMinMed":7.526,"tMaxMed":21.4255,"tMed":14.4751,"tMedSD":6.6035,"climate_type":4},{"indicativo":"2916A","nombre":"VITIGUDINO","provincia":"SALAMANCA","latitud":"410041N","longitud":"062616W","precTot":349,"precSD":3.5312,"tMinMed":6.7137,"tMaxMed":20.6769,"tMed":13.6928,"tMedSD":6.8119,"climate_type":4},{"indicativo":"2150H","nombre":"LA PINILLA, ESTACIÓN DE ESQUÍ","provincia":"SEGOVIA","latitud":"411131N","longitud":"032831W","precTot":969.6,"precSD":6.604,"tMinMed":4.5384,"tMaxMed":12.079,"tMed":8.3102,"tMedSD":7.1669,"climate_type":3},{"indicativo":"2465","nombre":"SEGOVIA","provincia":"SEGOVIA","latitud":"405643N","longitud":"040735W","precTot":397.9,"precSD":3.6639,"tMinMed":7.6353,"tMaxMed":19.2175,"tMed":13.4274,"tMedSD":7.1512,"climate_type":4},{"indicativo":"2030","nombre":"SORIA","provincia":"SORIA","latitud":"414630N","longitud":"022859W","precTot":382.4,"precSD":3.3583,"tMinMed":4.5391,"tMaxMed":17.2039,"tMed":10.8713,"tMedSD":6.261,"climate_type":3},{"indicativo":"2503X","nombre":"OLMEDO","provincia":"VALLADOLID","latitud":"411933N","longitud":"044113W","precTot":274.7,"precSD":2.2779,"tMinMed":5.9694,"tMaxMed":20.0197,"tMed":12.9962,"tMedSD":6.954,"climate_type":4},{"indicativo":"2539","nombre":"VALLADOLID AEROPUERTO","provincia":"VALLADOLID","latitud":"414243N","longitud":"045120W","precTot":346.8,"precSD":3.0193,"tMinMed":6.4392,"tMaxMed":18.5951,"tMed":12.5167,"tMedSD":6.7025,"climate_type":4},{"indicativo":"2422","nombre":"VALLADOLID","provincia":"VALLADOLID","latitud":"413827N","longitud":"044516W","precTot":324.9,"precSD":2.9843,"tMinMed":7.6625,"tMaxMed":19.9359,"tMed":13.7981,"tMedSD":6.968,"climate_type":4},{"indicativo":"2755X","nombre":"BENAVENTE","provincia":"ZAMORA","latitud":"420039N","longitud":"054000W","precTot":315.4,"precSD":3.169,"tMinMed":6.8207,"tMaxMed":19.6779,"tMed":13.2283,"tMedSD":6.611,"climate_type":4},{"indicativo":"2775X","nombre":"VILLARDECIERVOS","provincia":"ZAMORA","latitud":"415629N","longitud":"061647W","precTot":683,"precSD":5.3956,"tMinMed":4.0183,"tMaxMed":19.3194,"tMed":11.6677,"tMedSD":5.9992,"climate_type":3},{"indicativo":"2614","nombre":"ZAMORA","provincia":"ZAMORA","latitud":"413056N","longitud":"054407W","precTot":271.5,"precSD":2.3488,"tMinMed":7.7427,"tMaxMed":20.4288,"tMed":14.0849,"tMedSD":6.8891,"climate_type":4},{"indicativo":"3391","nombre":"SOTILLO DE LA ADRADA","provincia":"AVILA","latitud":"401719N","longitud":"043527W","precTot":401.3,"precSD":3.5219,"tMinMed":10.0239,"tMaxMed":23.7935,"tMed":16.9132,"tMedSD":7.4857,"climate_type":4},{"indicativo":"3469A","nombre":"CÁCERES","provincia":"CACERES","latitud":"392817N","longitud":"062020W","precTot":515.6,"precSD":4.4231,"tMinMed":11.1288,"tMaxMed":23.0052,"tMed":17.0666,"tMedSD":7.0968,"climate_type":4},{"indicativo":"3526X","nombre":"CORIA","provincia":"CACERES","latitud":"400013N","longitud":"063327W","precTot":613.4,"precSD":5.4114,"tMinMed":11.0667,"tMaxMed":23.5058,"tMed":17.2829,"tMedSD":7.1582,"climate_type":2},{"indicativo":"3434X","nombre":"NAVALMORAL DE LA MATA","provincia":"CACERES","latitud":"395645N","longitud":"053457W","precTot":445.2,"precSD":4.6473,"tMinMed":9.7928,"tMaxMed":23.8991,"tMed":16.8425,"tMedSD":7.4899,"climate_type":4},{"indicativo":"3519X","nombre":"PLASENCIA","provincia":"CACERES","latitud":"400235N","longitud":"060509W","precTot":644.8,"precSD":5.0614,"tMinMed":11.7618,"tMaxMed":22.4903,"tMed":17.1256,"tMedSD":7.1216,"climate_type":2},{"indicativo":"3463X","nombre":"TRUJILLO","provincia":"CACERES","latitud":"392857N","longitud":"055115W","precTot":407.9,"precSD":3.3484,"tMinMed":10.9625,"tMaxMed":21.7507,"tMed":16.3549,"tMedSD":7.106,"climate_type":4},{"indicativo":"3576X","nombre":"VALENCIA DE ALCÁNTARA","provincia":"CACERES","latitud":"392453N","longitud":"071352W","precTot":306.4,"precSD":4.3855,"tMinMed":9.5267,"tMaxMed":21.4601,"tMed":15.4965,"tMedSD":6.5118,"climate_type":4},{"indicativo":"3044X","nombre":"CAÑIZARES","provincia":"CUENCA","latitud":"403149N","longitud":"020900W","precTot":395.6,"precSD":4.3227,"tMinMed":4.7782,"tMaxMed":21.4098,"tMed":13.0917,"tMedSD":6.188,"climate_type":4},{"indicativo":"3094B","nombre":"TARANCÓN","provincia":"CUENCA","latitud":"400041N","longitud":"030117W","precTot":322.2,"precSD":2.881,"tMinMed":9.4736,"tMaxMed":21.2335,"tMed":15.3525,"tMedSD":7.7106,"climate_type":4},{"indicativo":"3168C","nombre":"GUADALAJARA, EL SERRANILLO","provincia":"GUADALAJARA","latitud":"403933N","longitud":"031024W","precTot":360.1,"precSD":3.6837,"tMinMed":7.9126,"tMaxMed":21.1039,"tMed":14.5151,"tMedSD":7.0179,"climate_type":4},{"indicativo":"3168D","nombre":"GUADALAJARA","provincia":"GUADALAJARA","latitud":"403749N","longitud":"030900W","precTot":106.8,"precSD":2.8106,"tMinMed":9.7797,"tMaxMed":22.502,"tMed":16.1353,"tMedSD":7.3082,"climate_type":4},{"indicativo":"3013","nombre":"MOLINA DE ARAGÓN","provincia":"GUADALAJARA","latitud":"405030N","longitud":"015244W","precTot":375.4,"precSD":4.0193,"tMinMed":3.6381,"tMaxMed":19.5679,"tMed":11.6055,"tMedSD":6.7563,"climate_type":3},{"indicativo":"3130C","nombre":"SIGÜENZA","provincia":"GUADALAJARA","latitud":"410511N","longitud":"023705W","precTot":359.2,"precSD":3.0416,"tMinMed":3.8299,"tMaxMed":19.1355,"tMed":11.4802,"tMedSD":6.5367,"climate_type":3},{"indicativo":"3100B","nombre":"ARANJUEZ","provincia":"MADRID","latitud":"400402N","longitud":"033246W","precTot":210.6,"precSD":2.9027,"tMinMed":8.1863,"tMaxMed":23.3857,"tMed":15.7829,"tMedSD":7.444,"climate_type":4},{"indicativo":"3110C","nombre":"BUITRAGO DEL LOZOYA","provincia":"MADRID","latitud":"410025N","longitud":"033649W","precTot":401.6,"precSD":4.1086,"tMinMed":5.0409,"tMaxMed":18.3613,"tMed":11.6978,"tMedSD":6.3142,"climate_type":3},{"indicativo":"3191E","nombre":"COLMENAR VIEJO","provincia":"MADRID","latitud":"404146N","longitud":"034554W","precTot":596.8,"precSD":4.5492,"tMinMed":9.5436,"tMaxMed":18.8479,"tMed":14.1964,"tMedSD":7.1992,"climate_type":4},{"indicativo":"3200","nombre":"GETAFE","provincia":"MADRID","latitud":"401758N","longitud":"034320W","precTot":290.3,"precSD":2.5171,"tMinMed":10.5688,"tMaxMed":21.9551,"tMed":16.2625,"tMedSD":7.5918,"climate_type":4},{"indicativo":"3129","nombre":"MADRID AEROPUERTO","provincia":"MADRID","latitud":"402800N","longitud":"033320W","precTot":314.7,"precSD":2.8811,"tMinMed":8.6271,"tMaxMed":22.0764,"tMed":15.3526,"tMedSD":7.2345,"climate_type":4},{"indicativo":"3194U","nombre":"MADRID, CIUDAD UNIVERSITARIA","provincia":"MADRID","latitud":"402706N","longitud":"034327W","precTot":289.1,"precSD":3.4831,"tMinMed":8.6193,"tMaxMed":21.8655,"tMed":15.2438,"tMedSD":7.2164,"climate_type":4},{"indicativo":"3196","nombre":"MADRID, CUATRO VIENTOS","provincia":"MADRID","latitud":"402232N","longitud":"034710W","precTot":334.3,"precSD":2.8196,"tMinMed":10.2107,"tMaxMed":21.8263,"tMed":16.02,"tMedSD":7.4099,"climate_type":4},{"indicativo":"3195","nombre":"MADRID, RETIRO","provincia":"MADRID","latitud":"402443N","longitud":"034041W","precTot":380.4,"precSD":3.1287,"tMinMed":10.9833,"tMaxMed":21.131,"tMed":16.0597,"tMedSD":7.4499,"climate_type":4},{"indicativo":"3266A","nombre":"PUERTO ALTO DEL LEÓN","provincia":"MADRID","latitud":"404223N","longitud":"040831W","precTot":628,"precSD":7.5518,"tMinMed":4.843,"tMaxMed":13.1108,"tMed":8.9776,"tMedSD":7.4063,"climate_type":3},{"indicativo":"3338","nombre":"ROBLEDO DE CHAVELA","provincia":"MADRID","latitud":"402540N","longitud":"041500W","precTot":359.1,"precSD":4.3904,"tMinMed":9.9952,"tMaxMed":21.4657,"tMed":15.7304,"tMedSD":6.785,"climate_type":4},{"indicativo":"3111D","nombre":"SOMOSIERRA","provincia":"MADRID","latitud":"410808N","longitud":"033449W","precTot":673.7,"precSD":5.3854,"tMinMed":5.3721,"tMaxMed":14.8397,"tMed":10.1026,"tMedSD":6.7172,"climate_type":3},{"indicativo":"3175","nombre":"TORREJÓN DE ARDOZ","provincia":"MADRID","latitud":"402919N","longitud":"032637W","precTot":411.4,"precSD":3.7318,"tMinMed":8.2622,"tMaxMed":21.8948,"tMed":15.0764,"tMedSD":7.1507,"climate_type":4},{"indicativo":"3298X","nombre":"SAN PABLO DE LOS MONTES","provincia":"TOLEDO","latitud":"393249N","longitud":"042102W","precTot":419.1,"precSD":4.9354,"tMinMed":9.6592,"tMaxMed":19.9534,"tMed":14.8071,"tMedSD":7.7476,"climate_type":4},{"indicativo":"3365A","nombre":"TALAVERA DE LA REINA","provincia":"TOLEDO","latitud":"395731N","longitud":"045149W","precTot":364.2,"precSD":3.2674,"tMinMed":9.4714,"tMaxMed":23.1165,"tMed":16.2945,"tMedSD":7.5562,"climate_type":4},{"indicativo":"3260B","nombre":"TOLEDO","provincia":"TOLEDO","latitud":"395305N","longitud":"040243W","precTot":289.6,"precSD":3.3728,"tMinMed":10.3934,"tMaxMed":23.4052,"tMed":16.9049,"tMedSD":7.7261,"climate_type":4},{"indicativo":"4452","nombre":"BADAJOZ AEROPUERTO","provincia":"BADAJOZ","latitud":"385300N","longitud":"064850W","precTot":476.6,"precSD":4.2155,"tMinMed":10.5266,"tMaxMed":24.4389,"tMed":17.4847,"tMedSD":6.7894,"climate_type":2},{"indicativo":"4358X","nombre":"DON BENITO","provincia":"BADAJOZ","latitud":"385720N","longitud":"055250W","precTot":361.4,"precSD":3.3806,"tMinMed":11.544,"tMaxMed":24.6784,"tMed":18.1131,"tMedSD":7.0028,"climate_type":2},{"indicativo":"4244X","nombre":"HERRERA DEL DUQUE","provincia":"BADAJOZ","latitud":"391010N","longitud":"050344W","precTot":369.4,"precSD":3.4585,"tMinMed":10.2867,"tMaxMed":22.6446,"tMed":16.4672,"tMedSD":7.1946,"climate_type":4},{"indicativo":"4511C","nombre":"JEREZ DE LOS CABALLEROS","provincia":"BADAJOZ","latitud":"381755N","longitud":"064554W","precTot":283.8,"precSD":3.6443,"tMinMed":9.3373,"tMaxMed":21.9571,"tMed":15.6505,"tMedSD":6.437,"climate_type":4},{"indicativo":"4386B","nombre":"LLERENA","provincia":"BADAJOZ","latitud":"381354N","longitud":"060101W","precTot":348.4,"precSD":3.5534,"tMinMed":8.9553,"tMaxMed":18.6131,"tMed":13.7857,"tMedSD":6.6839,"climate_type":4},{"indicativo":"4410X","nombre":"MÉRIDA","provincia":"BADAJOZ","latitud":"385457N","longitud":"062308W","precTot":317.5,"precSD":2.7653,"tMinMed":10.6017,"tMaxMed":24.7523,"tMed":17.6773,"tMedSD":6.6298,"climate_type":2},{"indicativo":"4121","nombre":"CIUDAD REAL","provincia":"CIUDAD REAL","latitud":"385921N","longitud":"035513W","precTot":359.9,"precSD":3.1991,"tMinMed":10.3803,"tMaxMed":22.8452,"tMed":16.6126,"tMedSD":7.7773,"climate_type":4},{"indicativo":"4220X","nombre":"PUEBLA DE DON RODRIGO","provincia":"CIUDAD REAL","latitud":"390501N","longitud":"043719W","precTot":104,"precSD":1.8059,"tMinMed":10.3035,"tMaxMed":25.0687,"tMed":17.6831,"tMedSD":6.9339,"climate_type":2},{"indicativo":"4103X","nombre":"TOMELLOSO","provincia":"CIUDAD REAL","latitud":"391009N","longitud":"030027W","precTot":311.2,"precSD":3.4562,"tMinMed":8.1659,"tMaxMed":22.2312,"tMed":15.1994,"tMedSD":7.7127,"climate_type":4},{"indicativo":"4147X","nombre":"VALDEPEÑAS","provincia":"CIUDAD REAL","latitud":"384502N","longitud":"032329W","precTot":292.2,"precSD":3.038,"tMinMed":9.7538,"tMaxMed":22.404,"tMed":16.0806,"tMedSD":7.8246,"climate_type":4},{"indicativo":"4148","nombre":"VISO DEL MARQUÉS","provincia":"CIUDAD REAL","latitud":"383105N","longitud":"033400W","precTot":61.6,"precSD":1.7752,"tMinMed":8.6503,"tMaxMed":20.0961,"tMed":14.3739,"tMedSD":7.1722,"climate_type":4},{"indicativo":"4267X","nombre":"HINOJOSA DEL DUQUE","provincia":"CORDOBA","latitud":"382955N","longitud":"050716W","precTot":131.8,"precSD":1.8877,"tMinMed":9.9848,"tMaxMed":23.6934,"tMed":16.841,"tMedSD":7.4778,"climate_type":4},{"indicativo":"4090Y","nombre":"SAN CLEMENTE","provincia":"CUENCA","latitud":"392500N","longitud":"022514W","precTot":317.6,"precSD":3.13,"tMinMed":7.6438,"tMaxMed":21.1805,"tMed":14.4143,"tMedSD":7.478,"climate_type":4},{"indicativo":"4560Y","nombre":"ALAJAR","provincia":"HUELVA","latitud":"375207N","longitud":"064030W","precTot":751.6,"precSD":7.454,"tMinMed":11.8,"tMaxMed":22.7682,"tMed":17.2843,"tMedSD":6.5634,"climate_type":1},{"indicativo":"4549Y","nombre":"AYAMONTE","provincia":"HUELVA","latitud":"371141N","longitud":"072342W","precTot":505.9,"precSD":5.0415,"tMinMed":13.3761,"tMaxMed":23.1597,"tMed":18.268,"tMedSD":5.2875,"climate_type":2},{"indicativo":"4642E","nombre":"HUELVA, RONDA ESTE","provincia":"HUELVA","latitud":"371642N","longitud":"065442W","precTot":507.7,"precSD":5.3979,"tMinMed":12.8436,"tMaxMed":24.9477,"tMed":18.8953,"tMedSD":5.8137,"climate_type":2},{"indicativo":"4067","nombre":"MADRIDEJOS","provincia":"TOLEDO","latitud":"392931N","longitud":"033142W","precTot":86.6,"precSD":1.588,"tMinMed":7.8518,"tMaxMed":21.7959,"tMed":14.8209,"tMedSD":8.0252,"climate_type":4},{"indicativo":"4061X","nombre":"QUINTANAR DE LA ORDEN","provincia":"TOLEDO","latitud":"393550N","longitud":"030254W","precTot":173.6,"precSD":2.2863,"climate_type":4},{"indicativo":"5973","nombre":"CÁDIZ","provincia":"CADIZ","latitud":"362959N","longitud":"061528W","precTot":93.2,"precSD":3.3016,"tMinMed":15.7181,"tMaxMed":22.2618,"tMed":18.991,"tMedSD":5.4276,"climate_type":2},{"indicativo":"5911A","nombre":"GRAZALEMA","provincia":"CADIZ","latitud":"364538N","longitud":"052227W","precTot":1195.8,"precSD":10.2527,"tMinMed":9.7085,"tMaxMed":19.476,"tMed":14.5935,"tMedSD":6.1569,"climate_type":1},{"indicativo":"5960","nombre":"JEREZ DE LA FRONTERA AEROPUERTO","provincia":"CADIZ","latitud":"364502N","longitud":"060321W","precTot":504.2,"precSD":5.1188,"tMinMed":12.65,"tMaxMed":25.9329,"tMed":19.2909,"tMedSD":6.1718,"climate_type":2},{"indicativo":"5910","nombre":"ROTA, BASE NAVAL","provincia":"CADIZ","latitud":"363820N","longitud":"061957W","precTot":443.8,"precSD":4.6382,"tMinMed":13.5414,"tMaxMed":23.8337,"tMed":18.6847,"tMedSD":5.5568,"climate_type":2},{"indicativo":"5972X","nombre":"SAN FERNANDO","provincia":"CADIZ","latitud":"362756N","longitud":"061220W","precTot":484,"precSD":5.4694,"tMinMed":15.9403,"tMaxMed":23.1499,"tMed":19.5434,"tMedSD":5.245,"climate_type":2},{"indicativo":"5995B","nombre":"VEJER DE LA FRONTERA","provincia":"CADIZ","latitud":"361444N","longitud":"055754W","precTot":583,"precSD":6.2306,"tMinMed":14.849,"tMaxMed":22.2989,"tMed":18.5711,"tMedSD":4.9874,"climate_type":2},{"indicativo":"5000C","nombre":"CEUTA","provincia":"CEUTA","latitud":"355319N","longitud":"052049W","precTot":804.9,"precSD":8.4425,"tMinMed":16.3807,"tMaxMed":22.0389,"tMed":19.2094,"tMedSD":4.434,"climate_type":1},{"indicativo":"5402","nombre":"CÓRDOBA AEROPUERTO","provincia":"CORDOBA","latitud":"375056N","longitud":"045048W","precTot":432.8,"precSD":3.9459,"tMinMed":12.4182,"tMaxMed":25.3413,"tMed":18.8824,"tMedSD":7.0298,"climate_type":2},{"indicativo":"5427X","nombre":"DOÑA MENCÍA","provincia":"CORDOBA","latitud":"373322N","longitud":"042114W","precTot":501.1,"precSD":4.6467,"tMinMed":12.5997,"tMaxMed":22.4211,"tMed":17.5094,"tMedSD":6.8684,"climate_type":2},{"indicativo":"5390Y","nombre":"VILLANUEVA DE CÓRDOBA","provincia":"CORDOBA","latitud":"381959N","longitud":"043632W","precTot":381,"precSD":3.875,"tMinMed":10.3525,"tMaxMed":21.3433,"tMed":15.8481,"tMedSD":7.2158,"climate_type":4},{"indicativo":"5047E","nombre":"BAZA","provincia":"GRANADA","latitud":"373021N","longitud":"024406W","precTot":263,"precSD":2.7908,"tMinMed":6.5036,"tMaxMed":21.7383,"tMed":14.0828,"tMedSD":7.2482,"climate_type":4},{"indicativo":"5530E","nombre":"GRANADA AEROPUERTO","provincia":"GRANADA","latitud":"371123N","longitud":"034722W","precTot":366.8,"precSD":3.3665,"tMinMed":9.2304,"tMaxMed":24.423,"tMed":16.8268,"tMedSD":7.2163,"climate_type":4},{"indicativo":"5514","nombre":"GRANADA BASE AÉREA","provincia":"GRANADA","latitud":"370814N","longitud":"033753W","precTot":364.1,"precSD":3.4534,"tMinMed":9.1649,"tMaxMed":23.1055,"tMed":16.1348,"tMedSD":7.1105,"climate_type":4},{"indicativo":"5051X","nombre":"HUÉSCAR","provincia":"GRANADA","latitud":"375140N","longitud":"023910W","precTot":93.6,"precSD":2.9833,"tMinMed":5.9867,"tMaxMed":19.9313,"tMed":12.9578,"tMedSD":5.6108,"climate_type":4},{"indicativo":"5582A","nombre":"LOJA","provincia":"GRANADA","latitud":"370940N","longitud":"040910W","precTot":276.7,"precSD":3.2721,"tMinMed":10.6417,"tMaxMed":23.1288,"tMed":16.9058,"tMedSD":7.8521,"climate_type":4},{"indicativo":"5860E","nombre":"MOGUER, EL ARENOSILLO","provincia":"HUELVA","latitud":"370553N","longitud":"064417W","precTot":473.8,"precSD":4.589,"tMinMed":12.5846,"tMaxMed":22.8624,"tMed":17.7208,"tMedSD":5.0157,"climate_type":2},{"indicativo":"5298X","nombre":"ANDÚJAR","provincia":"JAEN","latitud":"380123N","longitud":"040348W","precTot":375.1,"precSD":3.8927,"tMinMed":11.0727,"tMaxMed":26.4789,"tMed":18.7597,"tMedSD":7.3009,"climate_type":2},{"indicativo":"5181D","nombre":"ARROYO DEL OJANCO","provincia":"JAEN","latitud":"381853N","longitud":"025323W","precTot":343.9,"precSD":3.1185,"tMinMed":10.9621,"tMaxMed":23.496,"tMed":17.1994,"tMedSD":7.4504,"climate_type":4},{"indicativo":"5038X","nombre":"CAZORLA","provincia":"JAEN","latitud":"375457N","longitud":"030014W","precTot":431.4,"precSD":3.7651,"tMinMed":12.0242,"tMaxMed":22.2334,"tMed":17.1234,"tMedSD":7.6302,"climate_type":2},{"indicativo":"5270","nombre":"JAÉN, INSTITUTO","provincia":"JAEN","latitud":"374635N","longitud":"034720W","precTot":243.3,"precSD":3.3894,"climate_type":4},{"indicativo":"5270B","nombre":"JAÉN","provincia":"JAEN","latitud":"374639N","longitud":"034832W","precTot":375.7,"precSD":3.6842,"tMinMed":13.409,"tMaxMed":22.2742,"tMed":17.84,"tMedSD":7.221,"climate_type":2},{"indicativo":"5246","nombre":"SANTA ELENA","provincia":"JAEN","latitud":"382040N","longitud":"033207W","precTot":356.2,"precSD":3.6872,"tMinMed":10.846,"tMaxMed":22.5161,"tMed":16.6807,"tMedSD":8.106,"climate_type":4},{"indicativo":"5192","nombre":"VILLARRODRIGO","provincia":"JAEN","latitud":"382921N","longitud":"023815W","precTot":125,"precSD":2.3286,"tMinMed":12.6788,"tMaxMed":23.834,"tMed":18.2571,"tMedSD":7.5631,"climate_type":2},{"indicativo":"5704B","nombre":"CAZALLA DE LA SIERRA","provincia":"SEVILLA","latitud":"375535N","longitud":"054611W","precTot":574.9,"precSD":5.9112,"tMinMed":9.0184,"tMaxMed":21.581,"tMed":15.2985,"tMedSD":6.5309,"climate_type":4},{"indicativo":"5641X","nombre":"ÉCIJA","provincia":"SEVILLA","latitud":"373058N","longitud":"050506W","precTot":415.6,"precSD":4.0281,"tMinMed":11.7492,"tMaxMed":24.8256,"tMed":18.2882,"tMedSD":6.9727,"climate_type":2},{"indicativo":"5612B","nombre":"LA RODA DE ANDALUCÍA","provincia":"SEVILLA","latitud":"371140N","longitud":"044612W","precTot":390.4,"precSD":3.947,"tMinMed":10.4685,"tMaxMed":23.305,"tMed":16.8869,"tMedSD":6.7357,"climate_type":4},{"indicativo":"5796","nombre":"MORÓN DE LA FRONTERA","provincia":"SEVILLA","latitud":"370952N","longitud":"053641W","precTot":467.1,"precSD":4.0471,"tMinMed":12.5285,"tMaxMed":25.5912,"tMed":19.0578,"tMedSD":6.6835,"climate_type":2},{"indicativo":"5783","nombre":"SEVILLA AEROPUERTO","provincia":"SEVILLA","latitud":"372500N","longitud":"055245W","precTot":396.2,"precSD":4.0337,"tMinMed":14.3408,"tMaxMed":26.3636,"tMed":20.3496,"tMedSD":6.8332,"climate_type":2},{"indicativo":"6302A","nombre":"ABLA","provincia":"ALMERIA","latitud":"370829N","longitud":"024648W","precTot":197.6,"precSD":2.318,"tMinMed":9.9535,"tMaxMed":20.9244,"tMed":15.4335,"tMedSD":6.3827,"climate_type":4},{"indicativo":"6381","nombre":"ALBORÁN","provincia":"ALMERIA","latitud":"355618N","longitud":"030210W","precTot":161.8,"precSD":4.2688,"tMinMed":17.7973,"tMaxMed":21.1927,"tMed":19.4938,"tMedSD":3.6176,"climate_type":2},{"indicativo":"6325O","nombre":"ALMERÍA AEROPUERTO","provincia":"ALMERIA","latitud":"365047N","longitud":"022125W","precTot":145.4,"precSD":1.6038,"tMinMed":15.4875,"tMaxMed":23.339,"tMed":19.4136,"tMedSD":5.2643,"climate_type":2},{"indicativo":"6332X","nombre":"CARBONERAS","provincia":"ALMERIA","latitud":"365849N","longitud":"015413W","precTot":178,"precSD":2.7412,"tMinMed":16.3358,"tMaxMed":23.5474,"tMed":19.9291,"tMedSD":5.3286,"climate_type":2},{"indicativo":"6367B","nombre":"HUÉRCAL-OVERA","provincia":"ALMERIA","latitud":"372326N","longitud":"015637W","precTot":242.6,"precSD":2.4952,"tMinMed":11.418,"tMaxMed":22.7248,"tMed":17.0693,"tMedSD":6.3723,"climate_type":4},{"indicativo":"6293X","nombre":"ROQUETAS DE MAR","provincia":"ALMERIA","latitud":"364113N","longitud":"024206W","precTot":168,"precSD":2.9384,"tMinMed":14.5529,"tMaxMed":22.7414,"tMed":18.6514,"tMedSD":4.9038,"climate_type":2},{"indicativo":"6001","nombre":"TARIFA","provincia":"CADIZ","latitud":"360050N","longitud":"053556W","precTot":385.3,"precSD":5.3304,"tMinMed":14.1964,"tMaxMed":20.0339,"tMed":17.1159,"tMedSD":4.0866,"climate_type":2},{"indicativo":"6268X","nombre":"MOTRIL","provincia":"GRANADA","latitud":"364322N","longitud":"033149W","precTot":61.5,"precSD":5.305,"climate_type":4},{"indicativo":"6106X","nombre":"ANTEQUERA","provincia":"MALAGA","latitud":"370146N","longitud":"044454W","precTot":295.9,"precSD":3.7608,"tMinMed":11.1646,"tMaxMed":22.7246,"tMed":16.8411,"tMedSD":7.0862,"climate_type":4},{"indicativo":"6058I","nombre":"ESTEPONA","provincia":"MALAGA","latitud":"362501N","longitud":"050918W","precTot":629.9,"precSD":6.2691,"tMinMed":15.1346,"tMaxMed":23.4232,"tMed":19.2235,"tMedSD":4.6237,"climate_type":2},{"indicativo":"6084X","nombre":"FUENGIROLA","provincia":"MALAGA","latitud":"363219N","longitud":"043706W","precTot":572.2,"precSD":6.0799,"tMinMed":16.3952,"tMaxMed":22.7858,"tMed":19.5875,"tMedSD":4.2728,"climate_type":2},{"indicativo":"6155A","nombre":"MÁLAGA AEROPUERTO","provincia":"MALAGA","latitud":"363958N","longitud":"042856W","precTot":454.2,"precSD":4.7801,"tMinMed":14.9477,"tMaxMed":23.6559,"tMed":19.3008,"tMedSD":5.5284,"climate_type":2},{"indicativo":"6156X","nombre":"MÁLAGA, CENTRO METEOROLÓGICO","provincia":"MALAGA","latitud":"364304N","longitud":"042854W","precTot":410.4,"precSD":4.3711,"tMinMed":14.8037,"tMaxMed":23.6713,"tMed":19.2259,"tMedSD":5.2631,"climate_type":2},{"indicativo":"6032B","nombre":"RONDA","provincia":"MALAGA","latitud":"364459N","longitud":"051006W","precTot":0,"climate_type":4},{"indicativo":"6205X","nombre":"TORROX","provincia":"MALAGA","latitud":"364335N","longitud":"035726W","precTot":404.1,"precSD":4.9272,"tMinMed":14.9044,"tMaxMed":22.7267,"tMed":18.8187,"tMedSD":4.9802,"climate_type":2},{"indicativo":"6000A","nombre":"MELILLA","provincia":"MELILLA","latitud":"351635N","longitud":"025723W","precTot":273.6,"precSD":2.5998,"tMinMed":16.2775,"tMaxMed":22.4888,"tMed":19.3827,"tMedSD":4.8754,"climate_type":2},{"indicativo":"7096B","nombre":"HELLÍN","provincia":"ALBACETE","latitud":"383231N","longitud":"014211W","precTot":348.2,"precSD":4.0512,"tMinMed":10.4868,"tMaxMed":21.5795,"tMed":16.0334,"tMedSD":6.9484,"climate_type":4},{"indicativo":"7247X","nombre":"EL PINÓS/PINOSO","provincia":"ALICANTE","latitud":"382359N","longitud":"010217W","precTot":139.1,"precSD":1.6742,"tMinMed":8.3351,"tMaxMed":21.3851,"tMed":14.859,"tMedSD":5.7225,"climate_type":4},{"indicativo":"7002Y","nombre":"ÁGUILAS","provincia":"MURCIA","latitud":"372502N","longitud":"013513W","precTot":159.2,"precSD":1.7562,"tMinMed":15.5935,"tMaxMed":23.4092,"tMed":19.5037,"tMedSD":5.322,"climate_type":2},{"indicativo":"7228","nombre":"ALCANTARILLA, BASE AÉREA","provincia":"MURCIA","latitud":"375728N","longitud":"011343W","precTot":205.5,"precSD":3.3438,"tMinMed":12.0068,"tMaxMed":25.3622,"tMed":18.6825,"tMedSD":6.5802,"climate_type":2},{"indicativo":"7119B","nombre":"CARAVACA DE LA CRUZ","provincia":"MURCIA","latitud":"380609N","longitud":"015238W","precTot":310.4,"precSD":3.335,"tMinMed":8.5813,"tMaxMed":21.969,"tMed":15.2752,"tMedSD":6.7636,"climate_type":4},{"indicativo":"7012C","nombre":"CARTAGENA","provincia":"MURCIA","latitud":"373604N","longitud":"005916W","precTot":193.2,"precSD":2.0508,"tMinMed":16.578,"tMaxMed":23.1703,"tMed":19.8797,"tMedSD":5.2133,"climate_type":2},{"indicativo":"7145D","nombre":"CIEZA","provincia":"MURCIA","latitud":"381358N","longitud":"012250W","precTot":225.7,"precSD":2.4577,"tMinMed":11.4072,"tMaxMed":23.8192,"tMed":17.7009,"tMedSD":6.466,"climate_type":2},{"indicativo":"7209","nombre":"LORCA","provincia":"MURCIA","latitud":"373917N","longitud":"014114W","precTot":194.7,"precSD":2.2289,"tMinMed":12.4315,"tMaxMed":25.4116,"tMed":18.9181,"tMedSD":6.7555,"climate_type":2},{"indicativo":"7178I","nombre":"MURCIA","provincia":"MURCIA","latitud":"380007N","longitud":"011015W","precTot":227.2,"precSD":3.1729,"tMinMed":13.4901,"tMaxMed":25.7148,"tMed":19.6033,"tMedSD":6.5216,"climate_type":2},{"indicativo":"7031","nombre":"SAN JAVIER AEROPUERTO","provincia":"MURCIA","latitud":"374720N","longitud":"004812W","precTot":368,"precSD":8.2453,"tMinMed":14.2076,"tMaxMed":22.6099,"tMed":18.4501,"tMedSD":5.6724,"climate_type":2},{"indicativo":"7031X","nombre":"SAN JAVIER AEROPUERTO","provincia":"MURCIA","latitud":"374642N","longitud":"004821W","precTot":359.4,"precSD":8.2028,"tMinMed":13.7866,"tMaxMed":23.2972,"tMed":18.5426,"tMedSD":5.5627,"climate_type":2},{"indicativo":"7275C","nombre":"YECLA","provincia":"MURCIA","latitud":"383606N","longitud":"010935W","precTot":211.4,"precSD":2.7413,"tMinMed":9.1738,"tMaxMed":22.3376,"tMed":15.7086,"tMedSD":6.7744,"climate_type":4},{"indicativo":"8175","nombre":"ALBACETE BASE AÉREA","provincia":"ALBACETE","latitud":"385715N","longitud":"015123W","precTot":288.8,"precSD":2.4221,"tMinMed":8.7975,"tMaxMed":21.7627,"tMed":15.2814,"tMedSD":7.518,"climate_type":4},{"indicativo":"8178D","nombre":"ALBACETE","provincia":"ALBACETE","latitud":"390021N","longitud":"015146W","precTot":291,"precSD":2.5608,"tMinMed":9.7773,"tMaxMed":22.7959,"tMed":16.2863,"tMedSD":7.5023,"climate_type":4},{"indicativo":"8177A","nombre":"CHINCHILLA","provincia":"ALBACETE","latitud":"385609N","longitud":"013936W","precTot":123.2,"precSD":2.0883,"tMinMed":9.6107,"tMaxMed":22.1572,"tMed":15.8866,"tMedSD":7.3661,"climate_type":4},{"indicativo":"8025","nombre":"ALACANT/ALICANTE","provincia":"ALICANTE","latitud":"382221N","longitud":"002939W","precTot":300.2,"precSD":3.9794,"tMinMed":13.7085,"tMaxMed":24.0055,"tMed":18.8588,"tMedSD":5.6463,"climate_type":2},{"indicativo":"8019","nombre":"ALICANTE-ELCHE AEROPUERTO","provincia":"ALICANTE","latitud":"381658N","longitud":"003415W","precTot":245.4,"precSD":3.1012,"tMinMed":13.962,"tMaxMed":23.2829,"tMed":18.622,"tMedSD":5.7175,"climate_type":2},{"indicativo":"8050X","nombre":"JÁVEA/ XÀBIA","provincia":"ALICANTE","latitud":"384701N","longitud":"001004E","precTot":562.2,"precSD":7.6248,"tMinMed":12.9245,"tMaxMed":23.3796,"tMed":18.154,"tMedSD":5.7957,"climate_type":2},{"indicativo":"8500A","nombre":"CASTELLÓ - ALMASSORA","provincia":"CASTELLON","latitud":"395726N","longitud":"000419W","precTot":513.1,"precSD":5.9359,"tMinMed":13.9795,"tMaxMed":22.8353,"tMed":18.4066,"tMedSD":5.7513,"climate_type":2},{"indicativo":"8523X","nombre":"VINARÒS","provincia":"CASTELLON","latitud":"403315N","longitud":"002547E","precTot":495,"precSD":9.8732,"tMinMed":11.1164,"tMaxMed":22.8408,"tMed":16.9793,"tMedSD":5.7574,"climate_type":1},{"indicativo":"8096","nombre":"CUENCA","provincia":"CUENCA","latitud":"400402N","longitud":"020755W","precTot":441.8,"precSD":3.7118,"tMinMed":8.24,"tMaxMed":21.0279,"tMed":14.6359,"tMedSD":7.1745,"climate_type":4},{"indicativo":"8368U","nombre":"TERUEL","provincia":"TERUEL","latitud":"402102N","longitud":"010727W","precTot":378.1,"precSD":4.0133,"tMinMed":5.861,"tMaxMed":20.9937,"tMed":13.4269,"tMedSD":7.1861,"climate_type":4},{"indicativo":"8058X","nombre":"OLIVA","provincia":"VALENCIA","latitud":"385544N","longitud":"000545W","precTot":614.3,"precSD":9.046,"tMinMed":14.0166,"tMaxMed":22.7362,"tMed":18.3772,"tMedSD":5.6784,"climate_type":1},{"indicativo":"8325X","nombre":"POLINYÀ DE XÚQUER","provincia":"VALENCIA","latitud":"391105N","longitud":"002219W","precTot":592.2,"precSD":6.4769,"tMinMed":8.8613,"tMaxMed":17.1258,"tMed":13,"tMedSD":2.0638,"climate_type":3},{"indicativo":"8309X","nombre":"UTIEL","provincia":"VALENCIA","latitud":"393432N","longitud":"011441W","precTot":354.6,"precSD":3.4949,"tMinMed":7.2006,"tMaxMed":21.5355,"tMed":14.3713,"tMedSD":6.6391,"climate_type":4},{"indicativo":"8414A","nombre":"VALENCIA AEROPUERTO","provincia":"VALENCIA","latitud":"392906N","longitud":"002829W","precTot":409.1,"precSD":4.5447,"tMinMed":11.7686,"tMaxMed":22.3323,"tMed":17.051,"tMedSD":5.8055,"climate_type":4},{"indicativo":"8416Y","nombre":"VALÈNCIA, VIVEROS","provincia":"VALENCIA","latitud":"392850N","longitud":"002159W","precTot":418.4,"precSD":4.6304,"tMinMed":14.594,"tMaxMed":22.9536,"tMed":18.7736,"tMedSD":5.4027,"climate_type":2},{"indicativo":"8416","nombre":"VALÈNCIA","provincia":"VALENCIA","latitud":"392850N","longitud":"002159W","precTot":444.5,"precSD":5.0385,"tMinMed":14.4093,"tMaxMed":23.0203,"tMed":18.714,"tMedSD":5.4118,"climate_type":2},{"indicativo":"8293X","nombre":"XÀTIVA","provincia":"VALENCIA","latitud":"390006N","longitud":"003125W","precTot":338.4,"precSD":6.3426,"tMinMed":9.2994,"tMaxMed":21.7904,"tMed":15.5464,"tMedSD":5.2826,"climate_type":4},{"indicativo":"9091O","nombre":"FORONDA-TXOKIZA","provincia":"ARABA/ALAVA","latitud":"425255N","longitud":"024406W","precTot":503.6,"precSD":4.0301,"tMinMed":6.5838,"tMaxMed":18.6088,"tMed":12.5992,"tMedSD":5.6512,"climate_type":3},{"indicativo":"9091R","nombre":"VITORIA GASTEIZ AEROPUERTO","provincia":"ARABA/ALAVA","latitud":"425219N","longitud":"024358W","precTot":153.4,"precSD":4.458,"tMinMed":4.6183,"tMaxMed":16.0946,"tMed":10.3581,"tMedSD":3.9807,"climate_type":3},{"indicativo":"9111","nombre":"BELORADO","provincia":"BURGOS","latitud":"422516N","longitud":"031013W","precTot":499.9,"precSD":3.5898,"tMinMed":6.1923,"tMaxMed":17.5157,"tMed":11.8536,"tMedSD":5.9147,"climate_type":3},{"indicativo":"9051","nombre":"MEDINA DE POMAR","provincia":"BURGOS","latitud":"425512N","longitud":"032858W","precTot":382.2,"precSD":3.164,"tMinMed":5.8777,"tMaxMed":18.9023,"tMed":12.389,"tMedSD":5.7731,"climate_type":4},{"indicativo":"9001D","nombre":"REINOSA","provincia":"CANTABRIA","latitud":"425931N","longitud":"040938W","precTot":597.6,"precSD":5.1909,"tMinMed":3.9385,"tMaxMed":15.0416,"tMed":9.4893,"tMedSD":5.4697,"climate_type":3},{"indicativo":"9019B","nombre":"VALDERREDIBLE, POLIENTES   ","provincia":"CANTABRIA","latitud":"424823N","longitud":"035602W","precTot":438.3,"precSD":3.2709,"tMinMed":5.0089,"tMaxMed":17.5923,"tMed":11.2986,"tMedSD":5.5935,"climate_type":3},{"indicativo":"9563X","nombre":"CASTELLFORT","provincia":"CASTELLON","latitud":"402955N","longitud":"001112W","precTot":244.8,"precSD":3.3533,"tMinMed":7.5293,"tMaxMed":15.8266,"tMed":11.6792,"tMedSD":6.7611,"climate_type":3},{"indicativo":"9585","nombre":"LA MOLINA","provincia":"GIRONA","latitud":"421957N","longitud":"015622E","precTot":836.7,"precSD":8.9625,"tMinMed":4.4161,"tMaxMed":13.0015,"tMed":8.7092,"tMedSD":5.5455,"climate_type":3},{"indicativo":"9208E","nombre":"ARAGÜÉS DEL PUERTO","provincia":"HUESCA","latitud":"424232N","longitud":"004023W","precTot":523.3,"precSD":5.155,"tMinMed":4.5734,"tMaxMed":16.0598,"tMed":10.3139,"tMedSD":6.315,"climate_type":3},{"indicativo":"9784P","nombre":"BIELSA","provincia":"HUESCA","latitud":"423748N","longitud":"001329E","precTot":490.4,"precSD":6.1657,"tMinMed":6.5443,"tMaxMed":20.3278,"tMed":13.4368,"tMedSD":5.9135,"climate_type":4},{"indicativo":"9898","nombre":"HUESCA, AEROPUERTO","provincia":"HUESCA","latitud":"420504N","longitud":"001932W","precTot":371.8,"precSD":3.4,"tMinMed":9.4181,"tMaxMed":21.4047,"tMed":15.4099,"tMedSD":7.2162,"climate_type":4},{"indicativo":"9201K","nombre":"JACA","provincia":"HUESCA","latitud":"423444N","longitud":"003249W","precTot":367.1,"precSD":3.7456,"tMinMed":6.1774,"tMaxMed":18.3972,"tMed":12.2854,"tMedSD":6.5178,"climate_type":3},{"indicativo":"9814A","nombre":"TORLA","provincia":"HUESCA","latitud":"423736N","longitud":"000642W","precTot":650.9,"precSD":6.3051,"tMinMed":6.1746,"tMaxMed":18.2244,"tMed":12.1983,"tMedSD":5.9415,"climate_type":3},{"indicativo":"9170","nombre":"LOGROÑO, AEROPUERTO","provincia":"LA RIOJA","latitud":"422708N","longitud":"021952W","precTot":317.6,"precSD":3.1802,"tMinMed":8.9301,"tMaxMed":20.914,"tMed":14.9222,"tMedSD":6.5267,"climate_type":4},{"indicativo":"9619","nombre":"LA SEU D'URGELL","provincia":"LLEIDA","latitud":"422117N","longitud":"012747E","precTot":293.7,"precSD":2.8302,"tMinMed":8.8257,"tMaxMed":24.3257,"tMed":16.5755,"tMedSD":6.3167,"climate_type":4},{"indicativo":"9771C","nombre":"LLEIDA","provincia":"LLEIDA","latitud":"413734N","longitud":"003553E","precTot":291.6,"precSD":3.4307,"tMinMed":9.86,"tMaxMed":22.5438,"tMed":16.2014,"tMedSD":7.41,"climate_type":4},{"indicativo":"9990X","nombre":"NAUT ARAN, ARTIES ","provincia":"LLEIDA","latitud":"424201N","longitud":"005237E","precTot":320.8,"precSD":3.5499,"tMinMed":4.7571,"tMaxMed":16.8331,"tMed":10.7953,"tMedSD":6.1125,"climate_type":3},{"indicativo":"9698U","nombre":"TALARN","provincia":"LLEIDA","latitud":"421219N","longitud":"005155E","precTot":423.8,"precSD":5.0451,"tMinMed":9.5805,"tMaxMed":22.3964,"tMed":15.988,"tMedSD":6.0016,"climate_type":4},{"indicativo":"9720X","nombre":"TÀRREGA","provincia":"LLEIDA","latitud":"413902N","longitud":"010858E","precTot":320.7,"precSD":4.149,"tMinMed":10.1159,"tMaxMed":22.0359,"tMed":16.0783,"tMedSD":7.2497,"climate_type":4},{"indicativo":"9263X","nombre":"ARANGUREN, ILUNDAIN  ","provincia":"NAVARRA","latitud":"424634N","longitud":"013157W","precTot":345.2,"precSD":4.6009,"tMinMed":7.5522,"tMaxMed":18.5478,"tMed":13.049,"tMedSD":6.08,"climate_type":4},{"indicativo":"9294E","nombre":"BARDENAS REALES, BASE AÉREA","provincia":"NAVARRA","latitud":"421155N","longitud":"012831W","precTot":285,"precSD":3.5506,"tMinMed":9.5015,"tMaxMed":21.3495,"tMed":15.4232,"tMedSD":6.7927,"climate_type":4},{"indicativo":"9283X","nombre":"CADREITA","provincia":"NAVARRA","latitud":"421225N","longitud":"014241W","precTot":249.5,"precSD":3.4514,"tMinMed":5.4539,"tMaxMed":16.2352,"tMed":10.8443,"tMedSD":5.4275,"climate_type":3},{"indicativo":"9263D","nombre":"PAMPLONA, AEROPUERTO","provincia":"NAVARRA","latitud":"424637N","longitud":"013900W","precTot":511.6,"precSD":5.4444,"tMinMed":8.3159,"tMaxMed":20.1679,"tMed":14.2378,"tMedSD":6.37,"climate_type":4},{"indicativo":"9262","nombre":"PAMPLONA","provincia":"NAVARRA","latitud":"424904N","longitud":"013818W","precTot":543.8,"precSD":5.1061,"tMinMed":9.0756,"tMaxMed":19.397,"tMed":14.2334,"tMedSD":6.2903,"climate_type":4},{"indicativo":"9981A","nombre":"ESTACIÓN DE TORTOSA (ROQUETES)","provincia":"TARRAGONA","latitud":"404913N","longitud":"002936E","precTot":510.2,"precSD":6.4867,"tMinMed":13.0422,"tMaxMed":24.3219,"tMed":18.6814,"tMedSD":6.3521,"climate_type":2},{"indicativo":"9987P","nombre":"SANT JAUME D'ENVEJA","provincia":"TARRAGONA","latitud":"404157N","longitud":"004836E","precTot":214.2,"precSD":4.6556,"tMinMed":14.8714,"tMaxMed":18.2493,"tMed":15.2448,"tMedSD":5.3922,"climate_type":4},{"indicativo":"9573X","nombre":"ALCAÑIZ","provincia":"TERUEL","latitud":"410329N","longitud":"000830W","precTot":258.5,"precSD":3.0662,"tMinMed":8.6574,"tMaxMed":20.909,"tMed":14.7862,"tMedSD":6.944,"climate_type":4},{"indicativo":"9381I","nombre":"CALAMOCHA","provincia":"TERUEL","latitud":"405534N","longitud":"011736W","precTot":305.9,"precSD":2.6597,"tMinMed":5.4173,"tMaxMed":20.2167,"tMed":12.8162,"tMedSD":7.0047,"climate_type":4},{"indicativo":"9569A","nombre":"CALANDA","provincia":"TERUEL","latitud":"405648N","longitud":"001416W","precTot":185.6,"precSD":4.226,"tMinMed":13.8781,"tMaxMed":26.3741,"tMed":20.1229,"tMedSD":4.7642,"climate_type":2},{"indicativo":"9576C","nombre":"BUJARALOZ","provincia":"ZARAGOZA","latitud":"413121N","longitud":"001028W","precTot":146,"precSD":2.3425,"tMinMed":11.6564,"tMaxMed":25.1658,"tMed":18.412,"tMedSD":6.4184,"climate_type":2},{"indicativo":"9394X","nombre":"CALATAYUD","provincia":"ZARAGOZA","latitud":"411952N","longitud":"013843W","precTot":287.3,"precSD":3.9664,"tMinMed":9.2072,"tMaxMed":23.5506,"tMed":16.3806,"tMedSD":6.3449,"climate_type":4},{"indicativo":"9390","nombre":"DAROCA","provincia":"ZARAGOZA","latitud":"410652N","longitud":"012436W","precTot":371.6,"precSD":3.6143,"tMinMed":7.0156,"tMaxMed":21.0592,"tMed":14.0381,"tMedSD":7.2244,"climate_type":4},{"indicativo":"9244X","nombre":"SOS DEL REY CATÓLICO","provincia":"ZARAGOZA","latitud":"422927N","longitud":"011249W","precTot":308.3,"precSD":4.4854,"tMinMed":8.4059,"tMaxMed":19.5072,"tMed":13.9569,"tMedSD":6.608,"climate_type":4},{"indicativo":"9434","nombre":"ZARAGOZA, AEROPUERTO","provincia":"ZARAGOZA","latitud":"413938N","longitud":"010015W","precTot":318.5,"precSD":3.258,"tMinMed":10.9953,"tMaxMed":22.329,"tMed":16.6625,"tMedSD":7.232,"climate_type":4},{"indicativo":"B569X","nombre":"CAPDEPERA","provincia":"ILLES BALEARS","latitud":"394300N","longitud":"032841E","precTot":340,"precSD":3.5422,"tMinMed":15.883,"tMaxMed":21.3957,"tMed":18.6386,"tMedSD":5.1524,"climate_type":2},{"indicativo":"B013X","nombre":"ESCORCA, LLUC","provincia":"ILLES BALEARS","latitud":"394924N","longitud":"025309E","precTot":909.7,"precSD":9.8719,"tMinMed":8.5767,"tMaxMed":19.4522,"tMed":14.0155,"tMedSD":5.9427,"climate_type":1},{"indicativo":"B954","nombre":"IBIZA, AEROPUERTO","provincia":"ILLES BALEARS","latitud":"385235N","longitud":"012304E","precTot":456.4,"precSD":4.9861,"tMinMed":14.6466,"tMaxMed":22.5019,"tMed":18.5742,"tMedSD":5.5669,"climate_type":2},{"indicativo":"B893","nombre":"MENORCA, AEROPUERTO","provincia":"ILLES BALEARS","latitud":"395117N","longitud":"041256E","precTot":592.9,"precSD":6.1151,"tMinMed":13.8458,"tMaxMed":21.4288,"tMed":17.6351,"tMedSD":5.3451,"climate_type":2},{"indicativo":"B278","nombre":"PALMA DE MALLORCA, AEROPUERTO","provincia":"ILLES BALEARS","latitud":"393339N","longitud":"024412E","precTot":480.9,"precSD":4.3728,"tMinMed":11.8153,"tMaxMed":23.1625,"tMed":17.4899,"tMedSD":5.8551,"climate_type":2},{"indicativo":"B228","nombre":"PALMA, PUERTO","provincia":"ILLES BALEARS","latitud":"393319N","longitud":"023731E","precTot":512.9,"precSD":4.8532,"tMinMed":15.157,"tMaxMed":22.4493,"tMed":18.8019,"tMedSD":5.3118,"climate_type":2},{"indicativo":"B346X","nombre":"PORRERES","provincia":"ILLES BALEARS","latitud":"393118N","longitud":"030109E","precTot":330.5,"precSD":4.0245,"tMinMed":11.928,"tMaxMed":22.5898,"tMed":17.2807,"tMedSD":5.8394,"climate_type":2},{"indicativo":"B434X","nombre":"PORTOCOLOM  ","provincia":"ILLES BALEARS","latitud":"392452N","longitud":"031618E","precTot":280.8,"precSD":3.6953,"tMinMed":14.6957,"tMaxMed":22.1812,"tMed":18.4388,"tMedSD":5.2762,"climate_type":2},{"indicativo":"B691Y","nombre":"SA POBLA","provincia":"ILLES BALEARS","latitud":"394457N","longitud":"030100E","precTot":313,"precSD":5.4405,"tMinMed":14.1028,"tMaxMed":26.2656,"tMed":20.1834,"tMedSD":5.0029,"climate_type":2},{"indicativo":"B248","nombre":"SIERRA DE ALFABIA, BUNYOLA","provincia":"ILLES BALEARS","latitud":"394406N","longitud":"024247E","precTot":493.9,"precSD":12.0354,"tMinMed":6.8755,"tMaxMed":11.7319,"tMed":9.3085,"tMedSD":5.1542,"climate_type":3},{"indicativo":"C249I","nombre":"FUERTEVENTURA AEROPUERTO","provincia":"LAS PALMAS","latitud":"282641N","longitud":"135147W","precTot":112.6,"precSD":2.0543,"tMinMed":18.6937,"tMaxMed":25.3438,"tMed":22.0179,"tMedSD":2.8609,"climate_type":2},{"indicativo":"C649I","nombre":"GRAN CANARIA AEROPUERTO","provincia":"LAS PALMAS","latitud":"275504N","longitud":"152343W","precTot":81.7,"precSD":1.6501,"tMinMed":18.4973,"tMaxMed":24.3721,"tMed":21.4351,"tMedSD":2.6445,"climate_type":2},{"indicativo":"C029O","nombre":"LANZAROTE AEROPUERTO","provincia":"LAS PALMAS","latitud":"285707N","longitud":"133601W","precTot":133.6,"precSD":2.3195,"tMinMed":18.3753,"tMaxMed":25.4723,"tMed":21.9238,"tMedSD":3.0804,"climate_type":2},{"indicativo":"C659H","nombre":"LAS PALMAS DE GRAN CANARIA, SAN CRISTOBAL","provincia":"LAS PALMAS","latitud":"280523N","longitud":"152458W","precTot":140,"precSD":3.1934,"tMinMed":17.9014,"tMaxMed":22.1043,"tMed":20.0029,"tMedSD":2.0724,"climate_type":2},{"indicativo":"C689E","nombre":"MASPALOMAS","provincia":"LAS PALMAS","latitud":"274409N","longitud":"153545W","precTot":30.6,"precSD":0.704,"tMinMed":18.3927,"tMaxMed":24.4784,"tMed":21.444,"tMedSD":2.5042,"climate_type":2},{"indicativo":"C629X","nombre":"MOGÁN, PUERTO","provincia":"LAS PALMAS","latitud":"274859N","longitud":"154551W","precTot":59.1,"precSD":1.2593,"tMinMed":18.4982,"tMaxMed":26.2675,"tMed":22.3837,"tMedSD":2.6039,"climate_type":2},{"indicativo":"C839I","nombre":"TEGUISE","provincia":"LAS PALMAS","latitud":"291355N","longitud":"133007W","precTot":159.3,"precSD":3.3803,"tMinMed":17.2249,"tMaxMed":22.0498,"tMed":19.6376,"tMedSD":1.8081,"climate_type":2},{"indicativo":"C929I","nombre":"HIERRO AEROPUERTO","provincia":"STA. CRUZ DE TENERIFE","latitud":"274908N","longitud":"175320W","precTot":170.2,"precSD":2.0444,"tMinMed":19.4342,"tMaxMed":23.3413,"tMed":21.3848,"tMedSD":2.1874,"climate_type":2},{"indicativo":"C430E","nombre":"IZAÑA","provincia":"STA. CRUZ DE TENERIFE","latitud":"281832N","longitud":"162958W","precTot":207.1,"precSD":2.7868,"tMinMed":6.481,"tMaxMed":13.9482,"tMed":10.2091,"tMedSD":6.1511,"climate_type":3},{"indicativo":"C139E","nombre":"LA PALMA AEROPUERTO","provincia":"STA. CRUZ DE TENERIFE","latitud":"283759N","longitud":"174518W","precTot":269.1,"precSD":3.9445,"tMinMed":18.8478,"tMaxMed":23.6363,"tMed":21.2437,"tMedSD":2.3388,"climate_type":2},{"indicativo":"C459Z","nombre":"PUERTO DE LA CRUZ","provincia":"STA. CRUZ DE TENERIFE","latitud":"282505N","longitud":"163253W","precTot":273.2,"precSD":3.01,"tMinMed":17.942,"tMaxMed":23.771,"tMed":20.8553,"tMedSD":2.3851,"climate_type":2},{"indicativo":"C329Z","nombre":"SAN SEBASTIÁN DE LA GOMERA","provincia":"STA. CRUZ DE TENERIFE","latitud":"280523N","longitud":"170641W","precTot":100,"precSD":2.0398,"tMinMed":19.1644,"tMaxMed":24.2473,"tMed":21.7009,"tMedSD":2.7476,"climate_type":2},{"indicativo":"C449C","nombre":"STA.CRUZ DE TENERIFE","provincia":"STA. CRUZ DE TENERIFE","latitud":"282748N","longitud":"161519W","precTot":175.4,"precSD":2.7083,"tMinMed":18.6197,"tMaxMed":24.5619,"tMed":21.5904,"tMedSD":2.9986,"climate_type":2},{"indicativo":"C129Z","nombre":"TAZACORTE","provincia":"STA. CRUZ DE TENERIFE","latitud":"283545N","longitud":"175455W","precTot":223.9,"precSD":3.1419,"tMinMed":17.7924,"tMaxMed":24.5642,"tMed":21.1782,"tMedSD":2.7157,"climate_type":2},{"indicativo":"C447A","nombre":"TENERIFE NORTE AEROPUERTO","provincia":"STA. CRUZ DE TENERIFE","latitud":"282839N","longitud":"161946W","precTot":601.3,"precSD":6.0545,"tMinMed":13.3304,"tMaxMed":20.5008,"tMed":16.9148,"tMedSD":3.7763,"climate_type":1},{"indicativo":"C429I","nombre":"TENERIFE SUR AEROPUERTO","provincia":"STA. CRUZ DE TENERIFE","latitud":"280249N","longitud":"163340W","precTot":59.5,"precSD":1.3042,"tMinMed":17.4354,"tMaxMed":24.5099,"tMed":20.9728,"tMedSD":2.5639,"climate_type":2}]
